sixelplot/__init__.py
sixelplot-0.0.2.dist-info/DESCRIPTION.rst
sixelplot-0.0.2.dist-info/METADATA
sixelplot-0.0.2.dist-info/RECORD
sixelplot-0.0.2.dist-info/WHEEL
sixelplot-0.0.2.dist-info/metadata.json
sixelplot-0.0.2.dist-info/top_level.txt
