Metadata-Version: 2.0
Name: sixelplot
Version: 0.0.2
Summary: thin-wrapper for pysixel and matplotlib.
Home-page: https://github.com/kktk-KO/sixelplot
Author: kktk
Author-email: kktkko3579@gmail.com
License: CC0
Keywords: sixel terminal image
Platform: UNKNOWN
Classifier: Development Status :: 3 - Alpha
Classifier: Intended Audience :: Developers
Classifier: License :: CC0 1.0 Universal (CC0 1.0) Public Domain Dedication
Classifier: Programming Language :: Python :: 2
Classifier: Programming Language :: Python :: 3
Classifier: Topic :: Terminals
